{"cameraMode":{"drawMode":0,"name":"Shaded","section":"Shading Mode"},"sceneLighting":true,"audioPlay":false,"sceneViewState":{"m_AlwaysRefresh":false,"showFog":false,"showSkybox":false,"showFlares":false,"showImageEffects":false,"showParticleSystems":false,"showVisualEffectGraphs":true,"m_FxEnabled":true},"in2DMode":false,"pivot":{"x":0.5840131044387817,"y":-8.144298553466797,"z":8.643710136413575},"rotation":{"x":0.36296701431274416,"y":0.003313384484499693,"z":-0.0014853820903226734,"w":0.9319533705711365},"size":10.0,"orthographic":false}